ytb2audiobot/__init__.py
ytb2audiobot/audio.py
ytb2audiobot/autodownload.py
ytb2audiobot/commands.py
ytb2audiobot/config.py
ytb2audiobot/cron.py
ytb2audiobot/datadir.py
ytb2audiobot/for_extra_option.py
ytb2audiobot/for_subtitles.py
ytb2audiobot/gpt.py
ytb2audiobot/logger.py
ytb2audiobot/mp4mutagen.py
ytb2audiobot/predictor.py
ytb2audiobot/processing.py
ytb2audiobot/pytube.py
ytb2audiobot/quotes.py
ytb2audiobot/subtitles.py
ytb2audiobot/tasks_dramatiq.py
ytb2audiobot/tasks_heuy.py
ytb2audiobot/thumbnail.py
ytb2audiobot/timecodes.py
ytb2audiobot/utils.py
ytb2audiobot/ytb2audiobot.py
ytb2audiobot/ytdlp.py
ytb2audiobot-3434.dist-info/LICENSE.txt
ytb2audiobot-3434.dist-info/METADATA
ytb2audiobot-3434.dist-info/WHEEL
ytb2audiobot-3434.dist-info/entry_points.txt
ytb2audiobot-3434.dist-info/top_level.txt
ytb2audiobot-3434.dist-info/RECORD
